[
  {
    "id": 1,
    "discount": "-30%",
    "productName": "Coffee Retail Packs",
    "productWeight": "500 g",
    "priceBeforeSale": "14.99",
    "priceCurrent": "10.49",
    "availableInventory": "10"
  },
  {
    "id": 2,
    "discount": "-30%",
    "productName": "Brazil Blend Arabia",
    "productWeight": "500 g",
    "priceBeforeSale": "13.99",
    "priceCurrent": "11.89",
    "availableInventory": "1"
  },
  {
    "id": 3,
    "discount": "-25%",
    "productName": "Unicorn Blood Dark",
    "productWeight": "500 g",
    "priceBeforeSale": "16.50",
    "priceCurrent": "12.38",
    "availableInventory": "5"
  }
]